sinp_nomenclatures/__init__.py
sinp_nomenclatures/admin.py
sinp_nomenclatures/apps.py
sinp_nomenclatures/fixtures/.gitkeep
sinp_nomenclatures/fixtures/old_sinp_nomenclatures.json
sinp_nomenclatures/fixtures/sinp_dict_data_v1.0.json
sinp_nomenclatures/locale/fr/LC_MESSAGES/django.po
sinp_nomenclatures/manager.py
sinp_nomenclatures/migrations/0001_initial.py
sinp_nomenclatures/migrations/0002_remove_nomenclature_active_nomenclature_status_and_more.py
sinp_nomenclatures/migrations/0003_nomenclature_parents.py
sinp_nomenclatures/migrations/0004_alter_nomenclature_parents.py
sinp_nomenclatures/migrations/__init__.py
sinp_nomenclatures/models.py
sinp_nomenclatures/permissions.py
sinp_nomenclatures/serializers.py
sinp_nomenclatures/tests.py
sinp_nomenclatures/urls.py
sinp_nomenclatures/views.py
dj_sinp_nomenclatures-1.4.3.dist-info/METADATA
dj_sinp_nomenclatures-1.4.3.dist-info/WHEEL
dj_sinp_nomenclatures-1.4.3.dist-info/licenses/LICENSE
dj_sinp_nomenclatures-1.4.3.dist-info/RECORD
