Metadata-Version: 2.4
Name: dj_sinp_nomenclatures
Version: 1.4.3
Summary: Django app to manage french SINP nomenclatures standards
License: AGPLv3
License-File: LICENSE
Keywords: SINP,Nomenclatures,Django,France,dbChiroWeb
Author: dbChiro project
Author-email: project@dbchiro.org
Requires-Python: >=3.12,<4.0
Classifier: License :: Other/Proprietary License
Classifier: Programming Language :: Python :: 3
Classifier: Programming Language :: Python :: 3.12
Classifier: Programming Language :: Python :: 3.13
Classifier: Programming Language :: Python :: 3.14
Requires-Dist: Django (>=4)
Requires-Dist: django-filter (>=23.5)
Requires-Dist: djangorestframework (>=3.0,<4.0)
Project-URL: Documentation, https://dbchiro.github.io/DjangoSinpNomenclature/
Project-URL: Homepage, https://github.com/dbchiro/DjangoSinpNomenclature
Project-URL: Repository, https://github.com/dbchiro/DjangoSinpNomenclature
